{
    "name": "example",
    "prefix": "%#PLACEHOLDER",
    "placeholderMappings": {
        "Header": [
            "APPLICATION_NAME"
        ],
        "Hero": [
            "HERO_HEADING_TEXT",
            "HERO_SUBHEADING_TEXT"
        ],
        "Footer": [
            "APPLICATION_NAME",
            "FOOTER_TEXT"
        ]
    },
    "placeholders": {
        "APPLICATION_NAME": "Purrfect Paws",
        "HERO_HEADING_TEXT": "Introducing Kitten Mittens: Pawsitively Adorable Protection",
        "HERO_SUBHEADING_TEXT": "Keep your feline friend's paws cozy and your furniture scratch-free with our stylish and comfortable kitten mittens.",
        "FOOTER_TEXT": "\u00a9 2023 Purrfect Paws. All rights reserved. Bringing warmth to tiny toes, one mitten at a time."
    }
}